moneyapi/__init__.py
moneyapi/moneyapi.py
moneyapi-0.0.2.dist-info/LICENSE
moneyapi-0.0.2.dist-info/METADATA
moneyapi-0.0.2.dist-info/WHEEL
moneyapi-0.0.2.dist-info/top_level.txt
moneyapi-0.0.2.dist-info/RECORD
