Metadata-Version: 2.1
Name: moneyapi
Version: 0.0.2
Summary: This is the moneyapi http request package.
Home-page: UNKNOWN
Author: Mason Worthen
Author-email: datalockhostingllc@gmail.com
License: UNKNOWN
Keywords: python,moneyapi,API,financial
Platform: UNKNOWN
Classifier: Development Status :: 1 - Planning
Classifier: Intended Audience :: Developers
Classifier: Programming Language :: Python :: 3
Classifier: Operating System :: Unix
Classifier: Operating System :: MacOS :: MacOS X
Classifier: Operating System :: Microsoft :: Windows
Requires-Dist: requests
